identity_clustering_exp/__init__.py
identity_clustering_exp/_version.py
identity_clustering_exp/cluster.py
identity_clustering_exp/dataset.py
identity_clustering_exp/facedetector.py
identity_clustering_exp/imports.py
identity_clustering_exp/utils.py
identity_clustering_exp/version.py
identity_clustering_exp-0.0.4.dist-info/METADATA
identity_clustering_exp-0.0.4.dist-info/WHEEL
identity_clustering_exp-0.0.4.dist-info/RECORD
